bdm_eng/TodayTarget.py
bdm_eng/__init__.py
bdm_eng/bant.py
bdm_eng/game_loop.py
bdm_eng/leadlist.py
bdm_eng/leadsource.py
bdm_eng/todaysactivity.py
bdm_eng/top100prospectleads.py
bdm_eng/top10targetsfortheweek.py
BDevManager2-0.0.13.dist-info/METADATA
BDevManager2-0.0.13.dist-info/WHEEL
BDevManager2-0.0.13.dist-info/top_level.txt
BDevManager2-0.0.13.dist-info/RECORD
