Metadata-Version: 2.1
Name: BDevManager2
Version: 0.0.13
Summary: A business development manager library
Home-page: https://github.com/BlackFoxgamingstudio/BDevManager2.git
Author: Russell Powers
Author-email: russell@blackfoxx45.com
Classifier: Programming Language :: Python :: 3
Classifier: License :: OSI Approved :: MIT License
Classifier: Operating System :: OS Independent
Requires-Dist: pandas
Requires-Dist: numpy
Requires-Dist: google-auth
Requires-Dist: google-auth-oauthlib
Requires-Dist: google-auth-httplib2
Requires-Dist: google-api-python-client
